punx/LICENSE.txt
punx/__init__.py
punx/_version.py
punx/cache_manager.py
punx/finding.py
punx/h5tree.py
punx/main.py
punx/nxdl_manager.py
punx/nxdl_schema.py
punx/nxdltree.py
punx/reserved_code.txt
punx/schema_manager.py
punx/singletons.py
punx/utils.py
punx/validate.py
punx/cache/a4fd52d/__github_info__.json
punx/cache/a4fd52d/nxdl.xsd
punx/cache/a4fd52d/nxdlTypes.xsd
punx/cache/a4fd52d/applications/NXarchive.nxdl.xml
punx/cache/a4fd52d/applications/NXarpes.nxdl.xml
punx/cache/a4fd52d/applications/NXdirecttof.nxdl.xml
punx/cache/a4fd52d/applications/NXfluo.nxdl.xml
punx/cache/a4fd52d/applications/NXindirecttof.nxdl.xml
punx/cache/a4fd52d/applications/NXiqproc.nxdl.xml
punx/cache/a4fd52d/applications/NXlauetof.nxdl.xml
punx/cache/a4fd52d/applications/NXmonopd.nxdl.xml
punx/cache/a4fd52d/applications/NXmx.nxdl.xml
punx/cache/a4fd52d/applications/NXrefscan.nxdl.xml
punx/cache/a4fd52d/applications/NXreftof.nxdl.xml
punx/cache/a4fd52d/applications/NXsas.nxdl.xml
punx/cache/a4fd52d/applications/NXsastof.nxdl.xml
punx/cache/a4fd52d/applications/NXscan.nxdl.xml
punx/cache/a4fd52d/applications/NXspe.nxdl.xml
punx/cache/a4fd52d/applications/NXsqom.nxdl.xml
punx/cache/a4fd52d/applications/NXstxm.nxdl.xml
punx/cache/a4fd52d/applications/NXtas.nxdl.xml
punx/cache/a4fd52d/applications/NXtofnpd.nxdl.xml
punx/cache/a4fd52d/applications/NXtofraw.nxdl.xml
punx/cache/a4fd52d/applications/NXtofsingle.nxdl.xml
punx/cache/a4fd52d/applications/NXtomo.nxdl.xml
punx/cache/a4fd52d/applications/NXtomophase.nxdl.xml
punx/cache/a4fd52d/applications/NXtomoproc.nxdl.xml
punx/cache/a4fd52d/applications/NXxas.nxdl.xml
punx/cache/a4fd52d/applications/NXxasproc.nxdl.xml
punx/cache/a4fd52d/applications/NXxbase.nxdl.xml
punx/cache/a4fd52d/applications/NXxeuler.nxdl.xml
punx/cache/a4fd52d/applications/NXxkappa.nxdl.xml
punx/cache/a4fd52d/applications/NXxlaue.nxdl.xml
punx/cache/a4fd52d/applications/NXxlaueplate.nxdl.xml
punx/cache/a4fd52d/applications/NXxnb.nxdl.xml
punx-0.3.5.dist-info/METADATA
punx-0.3.5.dist-info/WHEEL
punx-0.3.5.dist-info/entry_points.txt
punx-0.3.5.dist-info/top_level.txt
punx-0.3.5.dist-info/RECORD
