Metadata-Version: 2.1
Name: punx
Version: 0.3.5
Summary: Python Utilities for NeXus HDF5 files.
Author-email: Pete Jemian <prjemian@gmail.com>
License: Creative Commons Attribution 4.0 International Public License
Project-URL: Homepage, https://prjemian.github.io/punx/
Project-URL: Source, https://github.com/BCDA-APS/punx
Project-URL: Bug Tracker, https://github.com/BCDA-APS/punx/issues
Keywords: NeXus,HDF5
Classifier: Development Status :: 3 - Alpha
Classifier: Environment :: Console
Classifier: Intended Audience :: Science/Research
Classifier: License :: Freely Distributable
Classifier: License :: Public Domain
Classifier: Operating System :: OS Independent
Classifier: Programming Language :: Python :: 3
Classifier: Programming Language :: Python
Classifier: Topic :: Scientific/Engineering :: Astronomy
Classifier: Topic :: Scientific/Engineering :: Bio-Informatics
Classifier: Topic :: Scientific/Engineering :: Chemistry
Classifier: Topic :: Scientific/Engineering :: Information Analysis
Classifier: Topic :: Scientific/Engineering :: Interface Engine/Protocol Translator
Classifier: Topic :: Scientific/Engineering :: Mathematics
Classifier: Topic :: Scientific/Engineering :: Physics
Classifier: Topic :: Scientific/Engineering :: Visualization
Classifier: Topic :: Scientific/Engineering
Classifier: Topic :: Utilities
Requires-Python: >=3.8
Requires-Dist: h5py
Requires-Dist: hdf5plugin
Requires-Dist: lxml
Requires-Dist: numpy
Requires-Dist: PyQt5
Requires-Dist: pyRestTable
Requires-Dist: requests
